[
  {
    "id": 1,
    "name": "Грузчики",
    "description": "В услуги грузчиков входит: Погрузка и разгрузка вещей, их распределение в транспортном средстве Упаковка и распаковка груза Расстановка вещей, например, мебели, после переезда на новом месте Уборка помещения, из которого был осуществлен переезд.",
    "price": "200 руб/час.",
    "photo":"./services/for-search.jpg"
  },
  {
    "id": 3,
    "name": "Не Грузчики",
    "description": "Просто описание...",
    "price": "2000000 руб/час.",
    "photo":"./services/2.jpg"
  },
  {
    "id": 4,
    "name": "Что то другое",
    "description": "Здесь могла быть ваша реклама:)",
    "price": "0 руб/час. Бесплатно епта",
    "photo":"./services/for-search.jpg"
  }
]
